pypuregym/__init__.py
pypuregym/pure_api.py
pypuregym/utilities.py
pypuregym/cli/__init__.py
pypuregym/cli/book.py
pypuregym/cli/cli.py
pypuregym/cli/location.py
pypuregym/cli/schedule.py
pypuregym-1.7.0.dist-info/LICENSE
pypuregym-1.7.0.dist-info/METADATA
pypuregym-1.7.0.dist-info/WHEEL
pypuregym-1.7.0.dist-info/entry_points.txt
pypuregym-1.7.0.dist-info/top_level.txt
pypuregym-1.7.0.dist-info/RECORD
