Metadata-Version: 2.1
Name: pypuregym
Version: 1.7.0
Summary: A library to interact with Pure Fitness/Pure Yoga APIs.
Home-page: https://github.com/j-muller/pypuregym
Author: Jeffrey Muller
Author-email: hello@jeffrey.wtf
Classifier: Programming Language :: Python :: 3.6
Classifier: Programming Language :: Python :: 3.7
Classifier: Programming Language :: Python :: 3.8
License-File: LICENSE
Requires-Dist: requests <3.0.0,>=2.23.0
Requires-Dist: python-dateutil <3.0.0,>=2.8.1
Requires-Dist: docopt <1.0.0,>=0.6.2
Requires-Dist: tabulate <1.0.0,>=0.8.7
Provides-Extra: dev
Requires-Dist: ipython ; extra == 'dev'
Requires-Dist: pdbpp ; extra == 'dev'
Provides-Extra: doc
Requires-Dist: sphinx <2 ; extra == 'doc'
Provides-Extra: test
Requires-Dist: pytest ; extra == 'test'
Requires-Dist: pytest-cov ; extra == 'test'
Requires-Dist: pylint ; extra == 'test'
Requires-Dist: xenon ; extra == 'test'
Requires-Dist: pydocstyle ; extra == 'test'
Requires-Dist: pycodestyle ; extra == 'test'
Requires-Dist: cobertura-clover-transform ; extra == 'test'
